MANIFEST.in
README.md
setup.cfg
setup.py
example/__init__.py
example/bar3d_example.py
example/bar_example.py
example/boxplot_example.py
example/calendar_example.py
example/commons.py
example/effectscatter_example.py
example/funnel_example.py
example/gauge_example.py
example/geo_example.py
example/graph_eaxmple.py
example/grid_example.py
example/heatmap_example.py
example/kline_example.py
example/line3d_example.py
example/line_example.py
example/liquid_example.py
example/map_example.py
example/overlap_example.py
example/parallel_example.py
example/pie_example.py
example/polar_example.py
example/radar_example.py
example/sankey_example.py
example/scatter3d_example.py
example/scatter_example.py
example/surface3d_example.py
example/table_example.py
example/theme_example.py
example/themeriver_example.py
example/timeline_example.py
example/tree_example.py
example/treemap_example.py
example/wordcould_example.py
pyecharts/__init__.py
pyecharts/_version.py
pyecharts/exceptions.py
pyecharts/globals.py
pyecharts/charts/__init__.py
pyecharts/charts/base.py
pyecharts/charts/chart.py
pyecharts/charts/basic_charts/__init__.py
pyecharts/charts/basic_charts/bar.py
pyecharts/charts/basic_charts/boxplot.py
pyecharts/charts/basic_charts/calendar.py
pyecharts/charts/basic_charts/effectscatter.py
pyecharts/charts/basic_charts/funnel.py
pyecharts/charts/basic_charts/gauge.py
pyecharts/charts/basic_charts/geo.py
pyecharts/charts/basic_charts/graph.py
pyecharts/charts/basic_charts/heatmap.py
pyecharts/charts/basic_charts/kline.py
pyecharts/charts/basic_charts/line.py
pyecharts/charts/basic_charts/liquid.py
pyecharts/charts/basic_charts/map.py
pyecharts/charts/basic_charts/parallel.py
pyecharts/charts/basic_charts/pie.py
pyecharts/charts/basic_charts/polar.py
pyecharts/charts/basic_charts/radar.py
pyecharts/charts/basic_charts/sankey.py
pyecharts/charts/basic_charts/scatter.py
pyecharts/charts/basic_charts/themeriver.py
pyecharts/charts/basic_charts/tree.py
reactive_pyecharts.egg-info/PKG-INFO
reactive_pyecharts.egg-info/SOURCES.txt
reactive_pyecharts.egg-info/dependency_links.txt
reactive_pyecharts.egg-info/not-zip-safe
reactive_pyecharts.egg-info/requires.txt
reactive_pyecharts.egg-info/top_level.txt
