Metadata-Version: 2.1
Name: reactive-pyecharts
Version: 1.0.0
Summary: Python options, make charting easier
Home-page: https://github.com/pyecharts/pyecharts
Author: chenjiandongx
Author-email: chenjiandongx@qq.com
License: MIT
Keywords: Echarts,charts,plotting-tool
Platform: UNKNOWN
Classifier: Development Status :: 4 - Beta
Classifier: Environment :: Console
Classifier: Intended Audience :: Developers
Classifier: License :: OSI Approved :: MIT License
Classifier: Operating System :: OS Independent
Classifier: Programming Language :: Python
Classifier: Programming Language :: Python :: Implementation
Classifier: Programming Language :: Python :: 2
Classifier: Programming Language :: Python :: 2.7
Classifier: Programming Language :: Python :: 3
Classifier: Programming Language :: Python :: 3.5
Classifier: Programming Language :: Python :: 3.6
Classifier: Programming Language :: Python :: 3.7
Classifier: Topic :: Software Development :: Libraries
Provides-Extra: phantomjs
Provides-Extra: images
Provides-Extra: selenium
